src/interactive_CLI_menu_DexterH/__init__.py
src/interactive_CLI_menu_DexterH/funkymenu.py
funkymenu-0.0.6.dist-info/METADATA
funkymenu-0.0.6.dist-info/WHEEL
funkymenu-0.0.6.dist-info/licenses/LICENSE
funkymenu-0.0.6.dist-info/RECORD
